habitican_curse
