Metadata-Version: 1.0
Name: habitican-curse
Version: 2.2.6
Summary: Linux Terminal Application for Habitica
Home-page: https://github.com/rbavishi/Habitican-Curse
Author: Rohan Bavishi
Author-email: rohan.bavishi95@gmail.com
License: MIT
Platform: UNKNOWN
